{
  "e0fcbff4-7ae5-4083-8527-292693cc15e9": {
    "Website": null,
    "Logo": null,
    "Supporter Name": "",
    "Content": []
  },
  "caf4161d-4295-4137-a677-9ae2236893d9": {
    "Website": "https://www.amazon.in/",
    "Logo": "https://s3.us-west-2.amazonaws.com/secure.notion-static.com/5566be96-8706-4f63-90a1-520acdacea95/amazon.png?X-Amz-Algorithm=AWS4-HMAC-SHA256&X-Amz-Content-Sha256=UNSIGNED-PAYLOAD&X-Amz-Credential=AKIAT73L2G45EIPT3X45%2F20230912%2Fus-west-2%2Fs3%2Faws4_request&X-Amz-Date=20230912T114215Z&X-Amz-Expires=3600&X-Amz-Signature=0bdc6e80a6b8a184c94672406b7297c6491bc9e273015e3926a164a13ec3cec7&X-Amz-SignedHeaders=host&x-id=GetObject",
    "Supporter Name": "Amazon",
    "Content": []
  },
  "3967f0ab-22bc-49cb-952e-2cbcf997a59e": {
    "Website": "http://ncore.thenudge.org/",
    "Logo": "https://s3.us-west-2.amazonaws.com/secure.notion-static.com/5d68e179-0b09-436c-aec1-b60c778fa20a/ncore.jpg?X-Amz-Algorithm=AWS4-HMAC-SHA256&X-Amz-Content-Sha256=UNSIGNED-PAYLOAD&X-Amz-Credential=AKIAT73L2G45EIPT3X45%2F20230912%2Fus-west-2%2Fs3%2Faws4_request&X-Amz-Date=20230912T114215Z&X-Amz-Expires=3600&X-Amz-Signature=52b9f221992c13ec9587e9292be15428cbc5a9835dceeafb51f4bc12af2de567&X-Amz-SignedHeaders=host&x-id=GetObject",
    "Supporter Name": "N Core",
    "Content": []
  },
  "9dbe03cc-f85c-4cf7-aea1-493c6d089beb": {
    "Website": "https://www.socialalpha.org/",
    "Logo": "https://s3.us-west-2.amazonaws.com/secure.notion-static.com/755dd5bc-e08a-4b97-840f-d8dc5648ca00/social-alpha.jpg?X-Amz-Algorithm=AWS4-HMAC-SHA256&X-Amz-Content-Sha256=UNSIGNED-PAYLOAD&X-Amz-Credential=AKIAT73L2G45EIPT3X45%2F20230912%2Fus-west-2%2Fs3%2Faws4_request&X-Amz-Date=20230912T114216Z&X-Amz-Expires=3600&X-Amz-Signature=4ed3c0ab2c5912e8774deb3f77c13f8a7b31ccdbf2e7f88cf59cfd2d82016c30&X-Amz-SignedHeaders=host&x-id=GetObject",
    "Supporter Name": "Social Alpha",
    "Content": []
  },
  "c491dd45-d096-4e1e-ac11-4c74eb50a1fe": {
    "Website": "https://unltdindia.org/",
    "Logo": "https://s3.us-west-2.amazonaws.com/secure.notion-static.com/9be384ec-d6aa-4e83-90d1-df95cd97e7b5/unltd.jpg?X-Amz-Algorithm=AWS4-HMAC-SHA256&X-Amz-Content-Sha256=UNSIGNED-PAYLOAD&X-Amz-Credential=AKIAT73L2G45EIPT3X45%2F20230912%2Fus-west-2%2Fs3%2Faws4_request&X-Amz-Date=20230912T114215Z&X-Amz-Expires=3600&X-Amz-Signature=58908e824507ca3188f14e33b81268417dc7c670eaefa7dec7e17b2009155601&X-Amz-SignedHeaders=host&x-id=GetObject",
    "Supporter Name": "Un Ltd",
    "Content": []
  },
  "ddf0639d-ad4a-4893-a74c-b1c218b3dab8": {
    "Website": "https://www.dunnhumby.com/india/",
    "Logo": "https://s3.us-west-2.amazonaws.com/secure.notion-static.com/36642d4a-94a9-433f-a37f-58d06973c672/dunnhumby_logo.png?X-Amz-Algorithm=AWS4-HMAC-SHA256&X-Amz-Content-Sha256=UNSIGNED-PAYLOAD&X-Amz-Credential=AKIAT73L2G45EIPT3X45%2F20230912%2Fus-west-2%2Fs3%2Faws4_request&X-Amz-Date=20230912T114216Z&X-Amz-Expires=3600&X-Amz-Signature=de912556d7e14ad3ced113e934a011f365422a07388b5b6813ba4488738bcfb2&X-Amz-SignedHeaders=host&x-id=GetObject",
    "Supporter Name": "Dunnhumby",
    "Content": []
  },
  "16a94c34-c589-4155-998c-dc36d953ce46": {
    "Website": "https://www.games24x7.com/",
    "Logo": "https://s3.us-west-2.amazonaws.com/secure.notion-static.com/55072092-0b71-4c6d-b199-d0e2a1c43f89/games24x7.png?X-Amz-Algorithm=AWS4-HMAC-SHA256&X-Amz-Content-Sha256=UNSIGNED-PAYLOAD&X-Amz-Credential=AKIAT73L2G45EIPT3X45%2F20230912%2Fus-west-2%2Fs3%2Faws4_request&X-Amz-Date=20230912T114216Z&X-Amz-Expires=3600&X-Amz-Signature=94ac41dc8f8a76d25fdeb28077747c763dff91e0fb515a57db19c2eac36248b9&X-Amz-SignedHeaders=host&x-id=GetObject",
    "Supporter Name": "Games 24x7",
    "Content": []
  },
  "5847d604-dd8d-4916-a9be-6e3560274f2f": {
    "Website": "https://www.accenture.com/in-en",
    "Logo": "https://s3.us-west-2.amazonaws.com/secure.notion-static.com/f01e8dfd-939b-49e8-8a44-631c5f25b1b6/accenture.jpg?X-Amz-Algorithm=AWS4-HMAC-SHA256&X-Amz-Content-Sha256=UNSIGNED-PAYLOAD&X-Amz-Credential=AKIAT73L2G45EIPT3X45%2F20230912%2Fus-west-2%2Fs3%2Faws4_request&X-Amz-Date=20230912T114215Z&X-Amz-Expires=3600&X-Amz-Signature=0fdf73adca561fe47f9b6da686c494e82c92e25b9c6dc2487fe0ba0537539efb&X-Amz-SignedHeaders=host&x-id=GetObject",
    "Supporter Name": "Accenture",
    "Content": []
  },
  "783469ef-a4c5-441c-adc6-a6db4b92ab6a": {
    "Website": "https://www.microsoft.com/en-in",
    "Logo": "https://s3.us-west-2.amazonaws.com/secure.notion-static.com/c47bcc48-6390-4689-87c5-7122ceec3a2b/microsoft.jpg?X-Amz-Algorithm=AWS4-HMAC-SHA256&X-Amz-Content-Sha256=UNSIGNED-PAYLOAD&X-Amz-Credential=AKIAT73L2G45EIPT3X45%2F20230912%2Fus-west-2%2Fs3%2Faws4_request&X-Amz-Date=20230912T114216Z&X-Amz-Expires=3600&X-Amz-Signature=2cc8219046e90225a0f983806c52554023bff7462a12a5d6d2cd18267b9f219f&X-Amz-SignedHeaders=host&x-id=GetObject",
    "Supporter Name": "Microsoft",
    "Content": []
  }
}